yt_concate/__init__.py
yt_concate/main.py
yt_concate/settings.py
yt_concate/utils.py
yt_concate/pipeline/__init__.py
yt_concate/pipeline/pipeline.py
yt_concate/pipeline/steps/__init__.py
yt_concate/pipeline/steps/download_captions.py
yt_concate/pipeline/steps/get_video_list.py
yt_concate/pipeline/steps/postflight.py
yt_concate/pipeline/steps/preflight.py
yt_concate/pipeline/steps/step.py
rondolu_yt_concate-0.1.0.dist-info/METADATA
rondolu_yt_concate-0.1.0.dist-info/WHEEL
rondolu_yt_concate-0.1.0.dist-info/top_level.txt
rondolu_yt_concate-0.1.0.dist-info/RECORD
