Metadata-Version: 2.1
Name: rondolu-yt-concate
Version: 0.1.0
Summary: Produce a concatenated video of clips that mentioned a word from youtube channel
Home-page: https://github.com/rondolu/yt-concate
Author: Jacky Lu
Author-email: jackylu0937648512@gmail.com
License: MIT
Platform: UNKNOWN
Classifier: License :: OSI Approved :: MIT License
Classifier: Programming Language :: Python
Classifier: Programming Language :: Python :: 3
Classifier: Programming Language :: Python :: 3.6
Classifier: Programming Language :: Python :: Implementation :: CPython
Classifier: Programming Language :: Python :: Implementation :: PyPy
Requires-Python: >=3.6.0
Requires-Dist: pytube
Requires-Dist: python-dotenv
Requires-Dist: urllib3
Requires-Dist: request
